bitroom-0.1.5.dist-info/METADATA
bitroom-0.1.5.dist-info/WHEEL
bitroom-0.1.5.dist-info/entry_points.txt
bitroom-0.1.5.dist-info/licenses/LICENSE
bitroom/__init__.py
bitroom/__main__.py
bitroom/auth/__init__.py
bitroom/auth/auth.py
bitroom/auth/encrypt_js.py
bitroom/cli.py
bitroom/config.py
bitroom/room.py
bitroom/tui.css
bitroom/tui.py
bitroom-0.1.5.dist-info/RECORD
