Metadata-Version: 2.1
Name: bitroom
Version: 0.1.5
Summary: BIT 场地预约查询接口（bitroom）
Author-Email: Y.D.X. <73375426+YDX-2147483647@users.noreply.github.com>
License: MIT
Classifier: Programming Language :: Python :: 3
Classifier: Programming Language :: Python :: 3 :: Only
Classifier: Programming Language :: Python :: 3.10
Classifier: Programming Language :: Python :: 3.11
Classifier: License :: OSI Approved :: MIT License
Classifier: Operating System :: OS Independent
Classifier: Environment :: Console
Classifier: Framework :: AsyncIO
Classifier: Topic :: Home Automation
Classifier: Topic :: Utilities
Classifier: Typing :: Typed
Project-URL: Homepage, https://github.com/YDX-2147483647/bitroom
Project-URL: Repository, https://github.com/YDX-2147483647/bitroom
Project-URL: Bug tracker, https://github.com/YDX-2147483647/bitroom/issues
Requires-Python: >=3.10
Requires-Dist: PyExecJS>=1.5.1
Requires-Dist: httpx>=0.24.0
Requires-Dist: click>=8.1.3
Requires-Dist: platformdirs>=3.5.0
Requires-Dist: tomli>=2.0.1; python_version < "3.11"
Requires-Dist: more-itertools>=9.1.0
Requires-Dist: rich>=13.3.5; extra == "tui"
Requires-Dist: textual>=0.23.0; extra == "tui"
Provides-Extra: tui
